babyjubjub_py-0.1.1.dist-info/METADATA
babyjubjub_py-0.1.1.dist-info/WHEEL
babyjubjub_py-0.1.1.dist-info/licenses/LICENSE
babyjubjub_py/__init__.py
babyjubjub_py/babyjubjub_py.cpython-310-x86_64-linux-gnu.so
babyjubjub_py-0.1.1.dist-info/RECORD
