Metadata-Version: 2.4
Name: babyjubjub-py
Version: 0.1.1
Classifier: Development Status :: 4 - Beta
Classifier: Intended Audience :: Developers
Classifier: License :: OSI Approved :: Apache Software License
Classifier: Operating System :: POSIX :: Linux
Classifier: Operating System :: MacOS
Classifier: Operating System :: Microsoft :: Windows
Classifier: Programming Language :: Python :: 3
Classifier: Programming Language :: Python :: 3.10
Classifier: Programming Language :: Python :: 3.11
Classifier: Programming Language :: Rust
Classifier: Programming Language :: Python :: Implementation :: CPython
Classifier: Topic :: Security :: Cryptography
Classifier: Topic :: Software Development :: Libraries :: Python Modules
License-File: LICENSE
Summary: Fast Python bindings for the Baby JubJub elliptic curve (Research Prototype)
Keywords: cryptography,elliptic-curve,babyjubjub,zero-knowledge,zk-snark
Author: Elkana Tovey
License: Apache-2.0
Requires-Python: >=3.8
Project-URL: Repository, https://github.com/elkanatovey/babyjubjub-py
Project-URL: Documentation, https://github.com/elkanatovey/babyjubjub-py/blob/main/README.md
